setup.cfg
setup.py
strainer/__init__.py
strainer/almostequal.py
strainer/case.py
strainer/doctypes.py
strainer/log.py
strainer/middleware.py
strainer/operators.py
strainer/validate.py
strainer/wellformed.py
strainer/xhtmlify.py
strainer.egg-info/PKG-INFO
strainer.egg-info/SOURCES.txt
strainer.egg-info/dependency_links.txt
strainer.egg-info/entry_points.txt
strainer.egg-info/top_level.txt
strainer.egg-info/zip-safe