Metadata-Version: 1.0
Name: strainer
Version: 0.1.4
Summary: Tools to allow developers to cleanup web serialization objects (HTML, JSON, XHTML)
Home-page: UNKNOWN
Author: Tom Lynn and Chris Perkins
Author-email: chris@percious.com
License: MIT
Keywords: html xhtml json wsgi
Platform: UNKNOWN
